[
  {
    "description": "    Como usuario de la tienda SauceDemo\n    Quiero comprar productos exitosamente\n    Para verificar el correcto checkout de la tienda",
    "elements": [
      {
        "description": "",
        "id": "verificar-funcionamiento-del-carrito;agregar-un-articulo-al-carrito-y-verificar-su-precio",
        "keyword": "Scenario",
        "line": 17,
        "name": "Agregar un articulo al carrito y verificar su precio",
        "steps": [
          {
            "keyword": "Before",
            "hidden": true,
            "result": {
              "status": "passed",
              "duration": 1244883899
            }
          },
          {
            "arguments": [],
            "keyword": "Given ",
            "line": 9,
            "name": "que he ingresado en 'https://www.saucedemo.com/'",
            "match": {
              "location": "src\\features\\steps_definitions\\steps_items_verify.js:26"
            },
            "result": {
              "status": "passed",
              "duration": 1264167000
            }
          },
          {
            "arguments": [],
            "keyword": "When ",
            "line": 10,
            "name": "inicio sesion usuario 'standard_user' y contrase単a 'secret_sauce' a la tienda",
            "match": {
              "location": "src\\features\\steps_definitions\\steps_items_verify.js:32"
            },
            "result": {
              "status": "passed",
              "duration": 3041689699
            }
          },
          {
            "arguments": [],
            "keyword": "When ",
            "line": 11,
            "name": "agrego el siguiente item 'backpack' al carrito",
            "match": {
              "location": "src\\features\\steps_definitions\\steps_items_verify.js:39"
            },
            "result": {
              "status": "passed",
              "duration": 3882859500
            }
          },
          {
            "arguments": [],
            "keyword": "When ",
            "line": 12,
            "name": "verifico que el precio '$29.99' sea el indicado por la tienda",
            "match": {
              "location": "src\\features\\steps_definitions\\steps_items_verify.js:47"
            },
            "result": {
              "status": "passed",
              "duration": 1922286900
            }
          },
          {
            "arguments": [],
            "keyword": "Then ",
            "line": 13,
            "name": "el item se agrega al carrito",
            "match": {
              "location": "src\\features\\steps_definitions\\steps_items_verify.js:53"
            },
            "result": {
              "status": "passed",
              "duration": 1918829299
            }
          },
          {
            "arguments": [],
            "keyword": "Then ",
            "line": 14,
            "name": "y se verifica con exito su nombre pruducto y precio en $",
            "match": {
              "location": "src\\features\\steps_definitions\\steps_items_verify.js:58"
            },
            "result": {
              "status": "passed",
              "duration": 2446699
            }
          },
          {
            "keyword": "After",
            "hidden": true,
            "result": {
              "status": "passed",
              "duration": 120000
            }
          }
        ],
        "tags": [
          {
            "name": "@items-price",
            "line": 7
          }
        ],
        "type": "scenario"
      },
      {
        "description": "",
        "id": "verificar-funcionamiento-del-carrito;agregar-un-articulo-al-carrito-y-verificar-su-precio",
        "keyword": "Scenario",
        "line": 18,
        "name": "Agregar un articulo al carrito y verificar su precio",
        "steps": [
          {
            "keyword": "Before",
            "hidden": true,
            "result": {
              "status": "passed",
              "duration": 1129082600
            }
          },
          {
            "arguments": [],
            "keyword": "Given ",
            "line": 9,
            "name": "que he ingresado en 'https://www.saucedemo.com/'",
            "match": {
              "location": "src\\features\\steps_definitions\\steps_items_verify.js:26"
            },
            "result": {
              "status": "passed",
              "duration": 1212988400
            }
          },
          {
            "arguments": [],
            "keyword": "When ",
            "line": 10,
            "name": "inicio sesion usuario 'standard_user' y contrase単a 'secret_sauce' a la tienda",
            "match": {
              "location": "src\\features\\steps_definitions\\steps_items_verify.js:32"
            },
            "result": {
              "status": "passed",
              "duration": 3052319400
            }
          },
          {
            "arguments": [],
            "keyword": "When ",
            "line": 11,
            "name": "agrego el siguiente item 'bike-light' al carrito",
            "match": {
              "location": "src\\features\\steps_definitions\\steps_items_verify.js:39"
            },
            "result": {
              "status": "passed",
              "duration": 3903663900
            }
          },
          {
            "arguments": [],
            "keyword": "When ",
            "line": 12,
            "name": "verifico que el precio '$9.99' sea el indicado por la tienda",
            "match": {
              "location": "src\\features\\steps_definitions\\steps_items_verify.js:47"
            },
            "result": {
              "status": "passed",
              "duration": 1917610199
            }
          },
          {
            "arguments": [],
            "keyword": "Then ",
            "line": 13,
            "name": "el item se agrega al carrito",
            "match": {
              "location": "src\\features\\steps_definitions\\steps_items_verify.js:53"
            },
            "result": {
              "status": "passed",
              "duration": 1918589599
            }
          },
          {
            "arguments": [],
            "keyword": "Then ",
            "line": 14,
            "name": "y se verifica con exito su nombre pruducto y precio en $",
            "match": {
              "location": "src\\features\\steps_definitions\\steps_items_verify.js:58"
            },
            "result": {
              "status": "passed",
              "duration": 410000
            }
          },
          {
            "keyword": "After",
            "hidden": true,
            "result": {
              "status": "passed",
              "duration": 141499
            }
          }
        ],
        "tags": [
          {
            "name": "@items-price",
            "line": 7
          }
        ],
        "type": "scenario"
      },
      {
        "description": "",
        "id": "verificar-funcionamiento-del-carrito;agregar-un-articulo-al-carrito-y-verificar-su-precio",
        "keyword": "Scenario",
        "line": 19,
        "name": "Agregar un articulo al carrito y verificar su precio",
        "steps": [
          {
            "keyword": "Before",
            "hidden": true,
            "result": {
              "status": "passed",
              "duration": 1259336800
            }
          },
          {
            "arguments": [],
            "keyword": "Given ",
            "line": 9,
            "name": "que he ingresado en 'https://www.saucedemo.com/'",
            "match": {
              "location": "src\\features\\steps_definitions\\steps_items_verify.js:26"
            },
            "result": {
              "status": "passed",
              "duration": 1268075300
            }
          },
          {
            "arguments": [],
            "keyword": "When ",
            "line": 10,
            "name": "inicio sesion usuario 'standard_user' y contrase単a 'secret_sauce' a la tienda",
            "match": {
              "location": "src\\features\\steps_definitions\\steps_items_verify.js:32"
            },
            "result": {
              "status": "passed",
              "duration": 3047848000
            }
          },
          {
            "arguments": [],
            "keyword": "When ",
            "line": 11,
            "name": "agrego el siguiente item 'bolt-t-shirt' al carrito",
            "match": {
              "location": "src\\features\\steps_definitions\\steps_items_verify.js:39"
            },
            "result": {
              "status": "passed",
              "duration": 3925411900
            }
          },
          {
            "arguments": [],
            "keyword": "When ",
            "line": 12,
            "name": "verifico que el precio '$15.99' sea el indicado por la tienda",
            "match": {
              "location": "src\\features\\steps_definitions\\steps_items_verify.js:47"
            },
            "result": {
              "status": "passed",
              "duration": 1914684500
            }
          },
          {
            "arguments": [],
            "keyword": "Then ",
            "line": 13,
            "name": "el item se agrega al carrito",
            "match": {
              "location": "src\\features\\steps_definitions\\steps_items_verify.js:53"
            },
            "result": {
              "status": "passed",
              "duration": 1918038899
            }
          },
          {
            "arguments": [],
            "keyword": "Then ",
            "line": 14,
            "name": "y se verifica con exito su nombre pruducto y precio en $",
            "match": {
              "location": "src\\features\\steps_definitions\\steps_items_verify.js:58"
            },
            "result": {
              "status": "passed",
              "duration": 334099
            }
          },
          {
            "keyword": "After",
            "hidden": true,
            "result": {
              "status": "passed",
              "duration": 182900
            }
          }
        ],
        "tags": [
          {
            "name": "@items-price",
            "line": 7
          }
        ],
        "type": "scenario"
      },
      {
        "description": "",
        "id": "verificar-funcionamiento-del-carrito;agregar-un-articulo-al-carrito-y-verificar-su-precio",
        "keyword": "Scenario",
        "line": 20,
        "name": "Agregar un articulo al carrito y verificar su precio",
        "steps": [
          {
            "keyword": "Before",
            "hidden": true,
            "result": {
              "status": "passed",
              "duration": 1150620099
            }
          },
          {
            "arguments": [],
            "keyword": "Given ",
            "line": 9,
            "name": "que he ingresado en 'https://www.saucedemo.com/'",
            "match": {
              "location": "src\\features\\steps_definitions\\steps_items_verify.js:26"
            },
            "result": {
              "status": "passed",
              "duration": 1163660500
            }
          },
          {
            "arguments": [],
            "keyword": "When ",
            "line": 10,
            "name": "inicio sesion usuario 'standard_user' y contrase単a 'secret_sauce' a la tienda",
            "match": {
              "location": "src\\features\\steps_definitions\\steps_items_verify.js:32"
            },
            "result": {
              "status": "passed",
              "duration": 3034088200
            }
          },
          {
            "arguments": [],
            "keyword": "When ",
            "line": 11,
            "name": "agrego el siguiente item 'fleece-jacket' al carrito",
            "match": {
              "location": "src\\features\\steps_definitions\\steps_items_verify.js:39"
            },
            "result": {
              "status": "passed",
              "duration": 3900298099
            }
          },
          {
            "arguments": [],
            "keyword": "When ",
            "line": 12,
            "name": "verifico que el precio '$49.99' sea el indicado por la tienda",
            "match": {
              "location": "src\\features\\steps_definitions\\steps_items_verify.js:47"
            },
            "result": {
              "status": "passed",
              "duration": 1916492800
            }
          },
          {
            "arguments": [],
            "keyword": "Then ",
            "line": 13,
            "name": "el item se agrega al carrito",
            "match": {
              "location": "src\\features\\steps_definitions\\steps_items_verify.js:53"
            },
            "result": {
              "status": "passed",
              "duration": 1911691200
            }
          },
          {
            "arguments": [],
            "keyword": "Then ",
            "line": 14,
            "name": "y se verifica con exito su nombre pruducto y precio en $",
            "match": {
              "location": "src\\features\\steps_definitions\\steps_items_verify.js:58"
            },
            "result": {
              "status": "passed",
              "duration": 347500
            }
          },
          {
            "keyword": "After",
            "hidden": true,
            "result": {
              "status": "passed",
              "duration": 497600
            }
          }
        ],
        "tags": [
          {
            "name": "@items-price",
            "line": 7
          }
        ],
        "type": "scenario"
      }
    ],
    "id": "verificar-funcionamiento-del-carrito",
    "line": 1,
    "keyword": "Feature",
    "name": "Verificar funcionamiento del carrito",
    "tags": [],
    "uri": "src\\features\\scenarios\\saucedemo\\items_verify_data.feature"
  }
]